Workbook

Sheet Guide
B1: Venture Capital & Private Equity Toolkit
B2: IB Prep Studio practice template. Source: illustrative figures for a fictional company (ExampleCo). Replace with real filings (10-K / annual report).
B4: What this model does
B5: 1. VC Method: works back from an exit value and a target return to the post-money and pre-money valuation, adjusted for future dilution.
B6: 2. Cap Table: a Series A round with an option pool created pre-money (the 'option pool shuffle'), share price and ownership before and after.
B7: 3. Exit Waterfall: payouts to Series A (1x non-participating liquidation preference), founders, seed investors and option holders at different exit values.
B8: 4. PE Fund Waterfall: a European (whole-fund) distribution waterfall: return of capital, 8% preferred return, GP catch-up and 80/20 carried interest.
B10: How to use it
B11: 1. Each sheet is self-contained except the Exit Waterfall, which links (green) to the Cap Table.
B12: 2. Change the yellow inputs and follow the formulas down the page.
B13: 3. Then rebuild each sheet from a blank page. These four calculations come up often in VC and PE interviews and case studies.
B15: Practice drills
... B31: Link example

Sheet VC Method
A1: VC Method Valuation
A2: ($ in millions) Source: illustrative figures for a fictional company (ExampleCo). Replace with real filings (10-K / annual report).
A3: Legend: blue = input, yellow fill = key assumption to change, black = formula, green = link to another sheet.
A5: INPUTS
A6: Investment amount | B6: 5
A7: Revenue in exit year | B7: 60
A8: Exit EV / revenue multiple | B8: 5
A9: Years to exit | B9: 6
A10: Target IRR | B10: 0.4
A11: Expected dilution from future rounds | B11: 0.3
A13: VALUATION
A14: Exit value | B14: =B7*B8 -> 300
A15: Required MOIC = (1 + IRR) ^ years | B15: =(1+B10)^B9 -> 7.529536
A16: Post-money before dilution = exit value / MOIC | B16: =B14/B15 -> 39.843093
A17: Retention ratio = 1 - future dilution | B17: =1-B11 -> 0.7
A18: Post-money valuation (dilution-adjusted) | B18: =B16*B17 -> 27.890165
A19: Pre-money valuation | B19: =B18-B6 -> 22.890165
A20: Ownership required at close | B20: =B6/B18 -> 0.17927467
A21: Ownership at exit (after dilution) | B21: =B20*B17 -> 0.12549227
A22: Check: value of stake at exit / investment | B22: =B21*B14/B6 -> 7.529536
A23: The check should equal the required MOIC.
A25: SENSITIVITY: PRE-MONEY VALUATION (rows = target IRR, columns = exit EV/revenue)
B26: =MAX(0.5,$B$8+(-2)) -> 3 | C26: =MAX(0.5,$B$8+(-1)) -> 4 | D26: =MAX(0.5,$B$8+(0)) -> 5 | E26: =MAX(0.5,$B$8+(1)) -> 6 | F26: =MAX(0.5,$B$8+(2)) -> 7
A27: =$B$10+(-0.1) -> 0.3 | B27: =$B$7*B$26/(1+$A27)^$B$9*(1-$B$11)-$B$6 -> 21.104203 | C27: =$B$7*C$26/(1+$A27)^$B$9*(1-$B$11)-$B$6 -> 29.805603 | D27: =$B$7*D$26/(1+$A27)^$B$9*(1-$B$11)-$B$6 -> 38.507004 | E27: =$B$7*E$26/(1+$A27)^$B$9*(1-$B$11)-$B$6 -> 47.208405 | F27: =$B$7*F$26/(1+$A27)^$B$9*(1-$B$11)-$B$6 -> 55.909806
A28: =$B$10+(-0.05) -> 0.35 | B28: =$B$7*B$26/(1+$A28)^$B$9*(1-$B$11)-$B$6 -> 15.814594 | C28: =$B$7*C$26/(1+$A28)^$B$9*(1-$B$11)-$B$6 -> 22.752791 | D28: =$B$7*D$26/(1+$A28)^$B$9*(1-$B$11)-$B$6 -> 29.690989 | E28: =$B$7*E$26/(1+$A28)^$B$9*(1-$B$11)-$B$6 -> 36.629187 | F28: =$B$7*F$26/(1+$A28)^$B$9*(1-$B$11)-$B$6 -> 43.567385
A29: =$B$10+(0) -> 0.4 | B29: =$B$7*B$26/(1+$A29)^$B$9*(1-$B$11)-$B$6 -> 11.734099 | C29: =$B$7*C$26/(1+$A29)^$B$9*(1-$B$11)-$B$6 -> 17.312132 | D29: =$B$7*D$26/(1+$A29)^$B$9*(1-$B$11)-$B$6 -> 22.890165 | E29: =$B$7*E$26/(1+$A29)^$B$9*(1-$B$11)-$B$6 -> 28.468198 | F29: =$B$7*F$26/(1+$A29)^$B$9*(1-$B$11)-$B$6 -> 34.046231
A30: =$B$10+(0.05) -> 0.45 | B30: =$B$7*B$26/(1+$A30)^$B$9*(1-$B$11)-$B$6 -> 8.5569668 | C30: =$B$7*C$26/(1+$A30)^$B$9*(1-$B$11)-$B$6 -> 13.075956 | D30: =$B$7*D$26/(1+$A30)^$B$9*(1-$B$11)-$B$6 -> 17.594945 | E30: =$B$7*E$26/(1+$A30)^$B$9*(1-$B$11)-$B$6 -> 22.113934 | F30: =$B$7*F$26/(1+$A30)^$B$9*(1-$B$11)-$B$6 -> 26.632922
A31: =$B$10+(0.1) -> 0.5 | B31: =$B$7*B$26/(1+$A31)^$B$9*(1-$B$11)-$B$6 -> 6.0617284 | C31: =$B$7*C$26/(1+$A31)^$B$9*(1-$B$11)-$B$6 -> 9.7489712 | D31: =$B$7*D$26/(1+$A31)^$B$9*(1-$B$11)-$B$6 -> 13.436214 | E31: =$B$7*E$26/(1+$A31)^$B$9*(1-$B$11)-$B$6 -> 17.123457 | F31: =$B$7*F$26/(1+$A31)^$B$9*(1-$B$11)-$B$6 -> 20.8107

Sheet Cap Table
A1: Series A Cap Table (option pool created pre-money)
A2: (shares in millions, $ in millions except price per share) Source: illustrative figures for a fictional company (ExampleCo). Replace with real filings (10-K / annual report).
A3: Legend: blue = input, yellow fill = key assumption to change, black = formula, green = link to another sheet.
A5: INPUTS
A6: Founder shares | B6: 8
A7: Existing option pool shares | B7: 1
A8: Seed investor shares | B8: 1
A9: Series A pre-money valuation | B9: 20
A10: Series A investment | B10: 5
A11: Target option pool, % of post-money | B11: 0.15
A13: ROUND MECHANICS
A14: Existing fully diluted shares | B14: =SUM(B6:B8) -> 10
A15: Series A ownership post-money = investment / post-money | B15: =B10/(B9+B10) -> 0.2
A16: Post-money fully diluted shares | B16: =(B14-B7)/(1-B11-B15) -> 13.846154
A17: New option pool shares (added pre-money) | B17: =B16*B11-B7 -> 1.0769231
A18: Price per share ($) | B18: =(B9+B10)/B16 -> 1.8055556
A19: Series A shares issued | B19: =B10/B18 -> 2.7692308
A20: Effective pre-money for existing holders (price x existing shares) | B20: =B18*B14 -> 18.055556
A21: Check: shares add up | B21: =IF(ABS(B14+B17+B19-B16)<0.0001,"OK","ERROR") -> OK
A22: Target pool must be larger than the existing pool. The headline pre-money includes the new pool, so existing holders effectively get the lower 'effective' pre-money.
A24: Holder | B24: Pre-round shares | C24: Pre-round % | D24: Post-round shares | E24: Post-round % | F24: Value at post ($mm)
A25: Founders | B25: =B6 -> 8 | C25: =B25/$B$29 -> 0.8 | D25: =B6 -> 8 | E25: =D25/$D$29 -> 0.57777778 | F25: =D25*$B$18 -> 14.444444
A26: Seed investor | B26: =B8 -> 1 | C26: =B26/$B$29 -> 0.1 | D26: =B8 -> 1 | E26: =D26/$D$29 -> 0.072222222 | F26: =D26*$B$18 -> 1.8055556
A27: Option pool (existing + new) | B27: =B7 -> 1 | C27: =B27/$B$29 -> 0.1 | D27: =B7+B17 -> 2.0769231 | E27: =D27/$D$29 -> 0.15 | F27: =D27*$B$18 -> 3.75
A28: Series A investor | B28: 0 | C28: =B28/$B$29 -> 0 | D28: =B19 -> 2.7692308 | E28: =D28/$D$29 -> 0.2 | F28: =D28*$B$18 -> 5
A29: Total | B29: =SUM(B25:B28) -> 10 | C29: =SUM(C25:C28) -> 1 | D29: =SUM(D25:D28) -> 13.846154 | E29: =SUM(E25:E28) -> 1 | F29: =SUM(F25:F28) -> 25
A30: Check: total value = post-money | F30: =IF(ABS(F29-(B9+B10))<0.0001,"OK","ERROR") -> OK

Sheet Exit Waterfall
A1: Exit Waterfall: 1x Non-Participating Preferred
A2: ($ in millions) Source: illustrative figures for a fictional company (ExampleCo). Replace with real filings (10-K / annual report).
A3: Legend: blue = input, yellow fill = key assumption to change, black = formula, green = link to another sheet.
A5: INPUTS
A6: Liquidation preference multiple (x invested) | B6: 1
A7: Series A invested | B7: ='Cap Table'!B10 -> 5
A8: Series A shares | B8: ='Cap Table'!B19 -> 2.7692308
A9: Total fully diluted shares | B9: ='Cap Table'!B16 -> 13.846154
A10: Founder shares | B10: ='Cap Table'!B6 -> 8
A11: Seed shares | B11: ='Cap Table'!B8 -> 1
A12: Option pool shares | B12: ='Cap Table'!D27 -> 2.0769231
A13: Preference amount | B13: =B6*B7 -> 5
A14: Series A as-converted ownership | B14: =B8/B9 -> 0.2
A15: Exit value above which Series A converts | B15: =B13/B14 -> 25
A17: PAYOUTS BY EXIT VALUE
A18: Exit equity value | B18: 10 | C18: 25 | D18: 50 | E18: 100 | F18: 200 | G18: 500
A19: Series A decision | B19: =IF(B18*$B$14>$B$13,"Convert","Preference") -> Preference | C19: =IF(C18*$B$14>$B$13,"Convert","Preference") -> Preference | D19: =IF(D18*$B$14>$B$13,"Convert","Preference") -> Convert | E19: =IF(E18*$B$14>$B$13,"Convert","Preference") -> Convert | F19: =IF(F18*$B$14>$B$13,"Convert","Preference") -> Convert | G19: =IF(G18*$B$14>$B$13,"Convert","Preference") -> Convert
A20: Series A payout | B20: =IF(B19="Convert",B18*$B$14,MIN(B18,$B$13)) -> 5 | C20: =IF(C19="Convert",C18*$B$14,MIN(C18,$B$13)) -> 5 | D20: =IF(D19="Convert",D18*$B$14,MIN(D18,$B$13)) -> 10 | E20: =IF(E19="Convert",E18*$B$14,MIN(E18,$B$13)) -> 20 | F20: =IF(F19="Convert",F18*$B$14,MIN(F18,$B$13)) -> 40 | G20: =IF(G19="Convert",G18*$B$14,MIN(G18,$B$13)) -> 100
A21: Left for other holders | B21: =B18-B20 -> 5 | C21: =C18-C20 -> 20 | D21: =D18-D20 -> 40 | E21: =E18-E20 -> 80 | F21: =F18-F20 -> 160 | G21: =G18-G20 -> 400
A22: Founders | B22: =B21*$B$10/($B$9-$B$8) -> 3.6111111 | C22: =C21*$B$10/($B$9-$B$8) -> 14.444444 | D22: =D21*$B$10/($B$9-$B$8) -> 28.888889 | E22: =E21*$B$10/($B$9-$B$8) -> 57.777778 | F22: =F21*$B$10/($B$9-$B$8) -> 115.55556 | G22: =G21*$B$10/($B$9-$B$8) -> 288.88889
A23: Seed investor | B23: =B21*$B$11/($B$9-$B$8) -> 0.45138889 | C23: =C21*$B$11/($B$9-$B$8) -> 1.8055556 | D23: =D21*$B$11/($B$9-$B$8) -> 3.6111111 | E23: =E21*$B$11/($B$9-$B$8) -> 7.2222222 | F23: =F21*$B$11/($B$9-$B$8) -> 14.444444 | G23: =G21*$B$11/($B$9-$B$8) -> 36.111111
A24: Option holders | B24: =B21*$B$12/($B$9-$B$8) -> 0.9375 | C24: =C21*$B$12/($B$9-$B$8) -> 3.75 | D24: =D21*$B$12/($B$9-$B$8) -> 7.5 | E24: =E21*$B$12/($B$9-$B$8) -> 15 | F24: =F21*$B$12/($B$9-$B$8) -> 30 | G24: =G21*$B$12/($B$9-$B$8) -> 75
A25: Total distributed | B25: =B20+B22+B23+B24 -> 10 | C25: =C20+C22+C23+C24 -> 25 | D25: =D20+D22+D23+D24 -> 50 | E25: =E20+E22+E23+E24 -> 100 | F25: =F20+F22+F23+F24 -> 200 | G25: =G20+G22+G23+G24 -> 500
A26: Series A MOIC | B26: =B20/$B$7 -> 1 | C26: =C20/$B$7 -> 1 | D26: =D20/$B$7 -> 2 | E26: =E20/$B$7 -> 4 | F26: =F20/$B$7 -> 8 | G26: =G20/$B$7 -> 20
A27: Check | B27: =IF(ABS(B25-B18)<0.0001,"OK","ERROR") -> OK | C27: =IF(ABS(C25-C18)<0.0001,"OK","ERROR") -> OK | D27: =IF(ABS(D25-D18)<0.0001,"OK","ERROR") -> OK | E27: =IF(ABS(E25-E18)<0.0001,"OK","ERROR") -> OK | F27: =IF(ABS(F25-F18)<0.0001,"OK","ERROR") -> OK | G27: =IF(ABS(G25-G18)<0.0001,"OK","ERROR") -> OK
A29: Simplification: all options are treated as granted and exercised, ignoring strike prices; one preferred class only.

Sheet PE Fund Waterfall
A1: PE Fund Distribution Waterfall (European / whole-fund)
A2: ($ in millions) Source: illustrative figures for a fictional company (ExampleCo). Replace with real filings (10-K / annual report).
A3: Legend: blue = input, yellow fill = key assumption to change, black = formula, green = link to another sheet.
A5: INPUTS
A6: LP capital contributed | B6: 100
A7: Total proceeds to distribute | B7: 250
A8: Holding period (years, single exit) | B8: 5
A9: Preferred return (hurdle) | B9: 0.08
A10: Carried interest | B10: 0.2
A11: GP catch-up (% of distributions in that tier) | B11: 1
A13: WATERFALL
B14: Total | C14: To LPs | D14: To GP
A15: 1. Return of capital | B15: =MIN(B7,B6) -> 100 | C15: =B15 -> 100 | D15: =0 -> 0
A16: 2. Preferred return (compounded) | B16: =MIN(B7-B15,B6*((1+B9)^B8-1)) -> 46.932808 | C16: =B16 -> 46.932808 | D16: =0 -> 0
A17: 3. GP catch-up | B17: =MAX(0,MIN(B7-B15-B16,B16*B10/(B11-B10))) -> 11.733202 | C17: =B17*(1-B11) -> 0 | D17: =B17*B11 -> 11.733202
A18: 4. Remaining split (LP / GP) | B18: =B7-B15-B16-B17 -> 91.33399 | C18: =B18*(1-B10) -> 73.067192 | D18: =B18*B10 -> 18.266798
A19: Total | B19: =SUM(B15:B18) -> 250 | C19: =SUM(C15:C18) -> 220 | D19: =SUM(D15:D18) -> 30
A20: Check: total = proceeds | B20: =IF(ABS(B19-B7)<0.0001,"OK","ERROR") -> OK
A22: RETURNS
A23: Gross MOIC (before carry) | B23: =B7/B6 -> 2.5
A24: Gross IRR | B24: =B23^(1/B8)-1 -> 0.20112443
A25: LP net MOIC | B25: =C19/B6 -> 2.2
A26: LP net IRR | B26: =B25^(1/B8)-1 -> 0.17080491
A27: GP share of total profit | B27: =IF(B7>B6,D19/(B7-B6),0) -> 0.2
A28: Catch-up must be larger than the carry rate. Management fees are ignored.
